xurls/__init__.py
xurls/_regex.py
xurls/express.py
xurls/schemes.py
xurls/tlds.py
xurls/tlds_pseudo.py
xurls/unicode.py
xurls/xurls.py
pyxurls-0.1.3.dist-info/LICENSE
pyxurls-0.1.3.dist-info/METADATA
pyxurls-0.1.3.dist-info/WHEEL
pyxurls-0.1.3.dist-info/top_level.txt
pyxurls-0.1.3.dist-info/RECORD
