Metadata-Version: 2.1
Name: pyxurls
Version: 0.1.3
Summary: A regular expression based URL extractor which extracts URLs from text.
Home-page: https://github.com/andytzeng/pyxurls
Author: Andy Tzeng
Author-email: andytzeng@aol.tw
License: UNKNOWN
Keywords: url regex extract
Platform: UNKNOWN
Classifier: Development Status :: 3 - Alpha
Classifier: Intended Audience :: Developers
Classifier: License :: OSI Approved :: BSD License
Classifier: Operating System :: OS Independent
Classifier: Topic :: Software Development :: Libraries :: Python Modules
Classifier: Topic :: Text Processing
Classifier: Topic :: Text Processing :: General
Classifier: Programming Language :: Python :: 3.6
Classifier: Programming Language :: Python :: 3.7
Classifier: Programming Language :: Python :: 3.8
Classifier: Programming Language :: Python :: 3.9
Requires-Python: >=3.6
